RTL/mux_4_1.v

module mux_4_1 (
    
   input [15:0] input_1, 
   input [15:0] input_2,
   input [15:0] input_3,
   input [15:0] input_4,
   input reset,
   input clock,
   output reg [15:0] out
);


reg [1:0] select;


always @(posedge clock or posedge reset) begin

if (reset) begin 
    out <= 16'd0;
    select <= 2'd0;

end else begin
    case (select)
    2'b00 : out <= input_1;
    2'b01 : out <= input_2;
    2'b10 : out <= input_3;
    2'b11 : out <= input_4;
endcase
select <= select+1;
end



end


endmodule

Testbench/mux_tb_auto_sel.v
//this is a testbench for testing mux for handling input 

`include "mux_4_1.v"
module mux_auto_sel_tb;

reg clock;

reg [15:0] input_1,input_2,input_3,input_4;
reg reset;
reg [1:0] select;
wire [15:0] out;

 mux_4_1 mux_0 (
    
   .input_1(input_1), 
   .input_2(input_2),
   .input_3(input_3),
   .input_4(input_4),
   .reset(reset),
   .clock(clock),
   .out(out)
);



initial begin
	repeat(10)
		#5 clock <= ~clock;
end


initial begin
reset <= 1;
clock <= 0;
#1
input_1 <= 16'h0300;
input_2 <= 16'h0200;
input_3 <= 16'h0100;
input_4 <= 16'h0000;
reset <= 0;
#10
input_1 <= 16'h0300;
input_2 <= 16'h0200;
input_3 <= 16'h0100;
input_4 <= 16'h0000;
reset <= 0;
#40
input_1 <= 16'h0300;
input_2 <= 16'h0200;
input_3 <= 16'h0100;
input_4 <= 16'h0000;
reset <= 1;
#10;

end

initial begin
	$dumpfile("wave_mux_2.vcd");
	$dumpvars(0, mux_auto_sel_tb);
end


endmodule

Testbench/wave_mux_2.vcd
$date
	Sun Dec 29 23:30:35 2024
$end
$version
	Icarus Verilog
$end
$timescale
	1s
$end
$scope module mux_auto_sel_tb $end
$var wire 16 ! out [15:0] $end
$var reg 1 " clock $end
$var reg 16 # input_1 [15:0] $end
$var reg 16 $ input_2 [15:0] $end
$var reg 16 % input_3 [15:0] $end
$var reg 16 & input_4 [15:0] $end
$var reg 1 ' reset $end
$scope module mux_0 $end
$var wire 1 " clock $end
$var wire 16 ( input_1 [15:0] $end
$var wire 16 ) input_2 [15:0] $end
$var wire 16 * input_3 [15:0] $end
$var wire 16 + input_4 [15:0] $end
$var wire 1 ' reset $end
$var reg 16 , out [15:0] $end
$var reg 2 - select [1:0] $end
$upscope $end
$upscope $end
$enddefinitions $end
$comment Show the parameter values. $end
$dumpall
$end
#0
$dumpvars
b0 -
b0 ,
bx +
bx *
bx )
bx (
1'
bx &
bx %
bx $
bx #
0"
b0 !
$end
#1
0'
b0 &
b0 +
b100000000 %
b100000000 *
b1000000000 $
b1000000000 )
b1100000000 #
b1100000000 (
#5
b1 -
b1100000000 !
b1100000000 ,
1"
#10
0"
#15
b10 -
b1000000000 !
b1000000000 ,
1"
#20
0"
#25
b11 -
b100000000 !
b100000000 ,
1"
#30
0"
#35
b0 -
b0 !
b0 ,
1"
#40
0"
#45
b1 -
b1100000000 !
b1100000000 ,
1"
#50
0"
#51
b0 -
b0 !
b0 ,
1'
